scraperai/__init__.py
scraperai/exceptions.py
scraperai/models.py
scraperai/scraper.py
scraperai/cli/__init__.py
scraperai/cli/app.py
scraperai/cli/controller.py
scraperai/cli/model.py
scraperai/cli/utils.py
scraperai/cli/view.py
scraperai/crawlers/__init__.py
scraperai/crawlers/base.py
scraperai/crawlers/requests.py
scraperai/crawlers/selenium.py
scraperai/crawlers/webdriver/__init__.py
scraperai/crawlers/webdriver/base.py
scraperai/crawlers/webdriver/local.py
scraperai/crawlers/webdriver/manager.py
scraperai/crawlers/webdriver/remote.py
scraperai/crawlers/webdriver/storage.py
scraperai/crawlers/webdriver/useragents.py
scraperai/crawlers/webdriver/useragents.txt
scraperai/crawlers/webdriver/utils.py
scraperai/lm/__init__.py
scraperai/lm/base.py
scraperai/lm/openai.py
scraperai/parsers/__init__.py
scraperai/parsers/agent.py
scraperai/parsers/catalog_item_detector.py
scraperai/parsers/data_fields_extractor.py
scraperai/parsers/pagination_detector.py
scraperai/parsers/parserai.py
scraperai/parsers/utils.py
scraperai/parsers/webpage_classifier.py
scraperai/parsers/webpage_descriptor.py
scraperai/utils/__init__.py
scraperai/utils/data.py
scraperai/utils/html.py
scraperai/utils/image.py
tests/__init__.py
tests/settings.py
tests/test_classification.py
tests/test_detection.py
tests/test_extractor.py
tests/test_html_utils.py
tests/test_webdriver.py
scraperai-0.0.2.dist-info/LICENSE
scraperai-0.0.2.dist-info/METADATA
scraperai-0.0.2.dist-info/WHEEL
scraperai-0.0.2.dist-info/entry_points.txt
scraperai-0.0.2.dist-info/top_level.txt
scraperai-0.0.2.dist-info/RECORD
