Metadata-Version: 2.1
Name: scraperai
Version: 0.0.2
Summary: ScraperAI is an open-source, AI-powered tool designed to simplify web scraping for users of all skill levels.
Home-page: https://github.com/scraperai/scraperai
Author: Iakov Kaiumov
Author-email: help@scraper-ai.com
License: GPL-3.0 license
License-File: LICENSE
Requires-Dist: packaging ==23.2
Requires-Dist: langchain ==0.1.16
Requires-Dist: langchain-community
Requires-Dist: langchain-openai
Requires-Dist: langchain-text-splitters
Requires-Dist: openai
Requires-Dist: tiktoken
Requires-Dist: htmlmin
Requires-Dist: requests
Requires-Dist: beautifulsoup4
Requires-Dist: lxml
Requires-Dist: selenium ==4.9.1
Requires-Dist: webdriver-manager
Requires-Dist: numpy ==1.26.4
Requires-Dist: pandas
Requires-Dist: openpyxl
Requires-Dist: tabulate
Requires-Dist: python-dotenv
Requires-Dist: tqdm
Requires-Dist: retry
Requires-Dist: Pillow
Requires-Dist: pydantic
Requires-Dist: appdirs
Requires-Dist: click
